Tweets_Analyzer/__init__.py
Tweets_Analyzer/tweets_main.py
Tweets_Sentiment_Analyzer/__init__.py
Tweets_Sentiment_Analyzer/tweets_main.py
Tweets_Analyzer-0.1.dist-info/METADATA
Tweets_Analyzer-0.1.dist-info/WHEEL
Tweets_Analyzer-0.1.dist-info/top_level.txt
Tweets_Analyzer-0.1.dist-info/RECORD
