Metadata-Version: 2.1
Name: Tweets-Analyzer
Version: 0.1
Summary: A Python package for analyzing the sentiment of tweets.
Home-page: https://github.com/Aleksandr-Chelyshkin/Tweets_Sentiment_Analyzer.git
Author: Aleksandr
Author-email: novacyan545@gmail.com
Requires-Dist: tweepy
Requires-Dist: textblob
